{
  "name" : "ITT_Target_Dashboard_tp",
  "label" : "ITT Target Dashboard",
  "folder" : {
    "id" : "${App.Folder.Id}"
  },
  "dateVersion" : 1,
  "mobileDisabled" : false,
  "xmd" : {
    "measures" : [
      {
        "conditionalFormatting" : {
          "chartColor" : {
            "referenceField" : "sum_Procedures",
            "type" : "gradient",
            "parameters" : {
              "bins" : [
                {
                  "formatValue" : "#E84340"
                },
                {
                  "formatValue" : "#1674D9"
                }
              ]
            }
          }
        },
        "field" : "State_5_1.sum_Procedures",
        "format" : {
          "delimiters" : { }
        }
      }
    ],
    "derivedDimensions" : [ ],
    "organizations" : [ ],
    "showDetailsDefaultFields" : [ ],
    "dates" : [ ],
    "derivedMeasures" : [ ],
    "dimensions" : [
      {
        "recordDisplayFields" : [ ],
        "conditionalFormatting" : {
          "chartColor" : {
            "referenceField" : "sum_Procedures",
            "type" : "gradient",
            "parameters" : {
              "bins" : [
                {
                  "formatValue" : "#E84340"
                },
                {
                  "formatValue" : "#1674D9"
                }
              ]
            }
          }
        },
        "salesforceActions" : [ ],
        "field" : "State_5_1.ALL",
        "members" : [ ],
        "customActions" : [ ]
      },
      {
        "recordDisplayFields" : [ ],
        "conditionalFormatting" : { },
        "salesforceActions" : [ ],
        "field" : "Procedure_2_1.Name",
        "members" : [ ],
        "customActions" : [ ]
      }
    ]
  },
  "state" : {
    "dataSourceLinks" : [ ],
    "filters" : [
      {
        "dataset" : {
          "name" : "${App.Datasets.ITT_Target_Transformed_tp.Name}"
        },
        "dependent" : true,
        "fields" : [
          "Bucket"
        ],
        "locked" : false,
        "operator" : "in"
      },
      {
        "dataset" : {
          "name" : "${App.Datasets.ITT_Target_Transformed_tp.Name}"
        },
        "dependent" : true,
        "fields" : [
          "Procedure"
        ],
        "locked" : false,
        "operator" : "in"
      },
      {
        "dataset" : {
          "name" : "${App.Datasets.ITT_Target_Transformed_tp.Name}"
        },
        "dependent" : true,
        "fields" : [
          "Facility_Name"
        ],
        "locked" : false,
        "operator" : "in"
      },
      {
        "dataset" : {
          "name" : "${App.Datasets.ITT_Target_Transformed_tp.Name}"
        },
        "dependent" : true,
        "fields" : [
          "Last_Name"
        ],
        "locked" : false,
        "operator" : "in"
      },
      {
        "dataset" : {
          "name" : "${App.Datasets.ITT_Target_Transformed_tp.Name}"
        },
        "dependent" : true,
        "fields" : [
          "Practitioner_Specialty"
        ],
        "locked" : false,
        "operator" : "in"
      },
      {
        "dataset" : {
          "name" : "${App.Datasets.ITT_Target_Transformed_tp.Name}"
        },
        "dependent" : true,
        "fields" : [
          "City"
        ],
        "locked" : false,
        "operator" : "in"
      },
      {
        "dataset" : {
          "name" : "${App.Datasets.ITT_Target_Transformed_tp.Name}"
        },
        "dependent" : true,
        "fields" : [
          "Zip"
        ],
        "locked" : false,
        "operator" : "in"
      }
    ],
    "gridLayouts" : [
      {
        "name" : "Default",
        "numColumns" : 44,
        "pages" : [
          {
            "label" : "Target",
            "name" : "be520780-d7e5-4e59-8f51-c5c6c7720280",
            "navigationHidden" : false,
            "widgets" : [
              {
                "colspan" : 44,
                "column" : 0,
                "name" : "container_1",
                "row" : 0,
                "rowspan" : 9,
                "widgetStyle" : {
                  "backgroundColor" : "rgba(255, 255, 255, 0)",
                  "borderColor" : "#E6ECF2",
                  "borderEdges" : [ ],
                  "borderRadius" : 0,
                  "borderWidth" : 1
                }
              },
              {
                "colspan" : 38,
                "column" : 3,
                "name" : "text_2",
                "row" : 1,
                "rowspan" : 3,
                "widgetStyle" : {
                  "backgroundColor" : "rgba(255, 255, 255, 0)",
                  "borderColor" : "#E6ECF2",
                  "borderEdges" : [ ],
                  "borderRadius" : 0,
                  "borderWidth" : 1
                }
              },
              {
                "colspan" : 7,
                "column" : 8,
                "name" : "link_1",
                "row" : 5,
                "rowspan" : 3,
                "widgetStyle" : {
                  "backgroundColor" : "#091A3E",
                  "borderColor" : "#FFCD95",
                  "borderEdges" : [
                    "bottom"
                  ],
                  "borderRadius" : 8,
                  "borderWidth" : 4
                }
              },
              {
                "colspan" : 7,
                "column" : 15,
                "name" : "link_2",
                "row" : 5,
                "rowspan" : 3,
                "widgetStyle" : {
                  "backgroundColor" : "#091A3E",
                  "borderColor" : "#98B1FF",
                  "borderEdges" : [
                    "bottom"
                  ],
                  "borderRadius" : 8,
                  "borderWidth" : 4
                }
              },
              {
                "colspan" : 7,
                "column" : 22,
                "name" : "link_3",
                "row" : 5,
                "rowspan" : 3,
                "widgetStyle" : {
                  "backgroundColor" : "#091A3E",
                  "borderColor" : "#98B1FF",
                  "borderEdges" : [
                    "bottom"
                  ],
                  "borderRadius" : 8,
                  "borderWidth" : 4
                }
              },
              {
                "colspan" : 7,
                "column" : 29,
                "name" : "link_4",
                "row" : 5,
                "rowspan" : 3,
                "widgetStyle" : {
                  "backgroundColor" : "#091A3E",
                  "borderColor" : "#98B1FF",
                  "borderEdges" : [
                    "bottom"
                  ],
                  "borderRadius" : 8,
                  "borderWidth" : 4
                }
              },
              {
                "colspan" : 42,
                "column" : 0,
                "name" : "text_3",
                "row" : 8,
                "rowspan" : 1,
                "widgetStyle" : {
                  "backgroundColor" : "rgba(255, 255, 255, 0)",
                  "borderColor" : "#FFFFFF",
                  "borderEdges" : [
                    "top"
                  ],
                  "borderRadius" : 0,
                  "borderWidth" : 2
                }
              },
              {
                "colspan" : 40,
                "column" : 2,
                "name" : "filterpanel_1",
                "row" : 9,
                "rowspan" : 4,
                "widgetStyle" : {
                  "borderEdges" : [ ]
                }
              },
              {
                "colspan" : 10,
                "column" : 1,
                "name" : "number_1",
                "row" : 14,
                "rowspan" : 4,
                "widgetStyle" : {
                  "backgroundColor" : "rgba(255, 255, 255, 0)",
                  "borderColor" : "#98B1FF",
                  "borderEdges" : [ ],
                  "borderRadius" : 8,
                  "borderWidth" : 2
                }
              },
              {
                "colspan" : 16,
                "column" : 14,
                "name" : "chart_2",
                "row" : 16,
                "rowspan" : 27,
                "widgetStyle" : {
                  "borderEdges" : [ ]
                }
              },
              {
                "colspan" : 12,
                "column" : 31,
                "name" : "chart_3",
                "row" : 17,
                "rowspan" : 26,
                "widgetStyle" : {
                  "borderEdges" : [ ]
                }
              },
              {
                "colspan" : 12,
                "column" : 1,
                "name" : "chart_1",
                "row" : 18,
                "rowspan" : 24,
                "widgetStyle" : {
                  "borderEdges" : [ ]
                }
              },
              {
                "colspan" : 42,
                "column" : 1,
                "name" : "chart_4",
                "row" : 44,
                "rowspan" : 23,
                "widgetStyle" : {
                  "borderEdges" : [ ]
                }
              },
              {
                "colspan" : 42,
                "column" : 1,
                "name" : "table_1",
                "row" : 68,
                "rowspan" : 48,
                "widgetStyle" : {
                  "borderEdges" : [ ]
                }
              }
            ]
          }
        ],
        "rowHeight" : "fine",
        "selectors" : [ ],
        "style" : {
          "alignmentX" : "left",
          "alignmentY" : "top",
          "backgroundColor" : "#091A3E",
          "cellSpacingX" : 4,
          "cellSpacingY" : 0,
          "fit" : "original",
          "gutterColor" : "#C5D3E0"
        },
        "version" : 1.0
      }
    ],
    "layouts" : [ ],
    "steps" : {
      "Procedure_2_1" : {
        "broadcastFacet" : true,
        "datasets" : [
          {
            "name" : "${App.Datasets.ITT_Target_Transformed_tp.Name}"
          }
        ],
        "isGlobal" : false,
        "label" : "Procedure_2",
        "query" : {
          "query" : {
            "measures" : [
              [
                "sum",
                "Procedures"
              ]
            ],
            "groups" : [
              "Procedure",
              "Name",
              "Practitioner_NPI"
            ],
            "order" : [
              [
                "sum_Procedures",
                {
                  "ascending" : false
                }
              ]
            ]
          },
          "version" : -1.0
        },
        "receiveFacetSource" : {
          "mode" : "all",
          "steps" : [ ]
        },
        "selectMode" : "single",
        "type" : "aggregateflex",
        "useGlobal" : true,
        "visualizationParameters" : {
          "parameters" : {
            "autoFitMode" : "keepLabels",
            "bins" : {
              "breakpoints" : {
                "high" : 100,
                "low" : 0
              },
              "bands" : {
                "high" : {
                  "color" : "#008000",
                  "label" : ""
                },
                "low" : {
                  "color" : "#B22222",
                  "label" : ""
                },
                "medium" : {
                  "color" : "#ffa500",
                  "label" : ""
                }
              }
            },
            "showValues" : true,
            "legend" : {
              "descOrder" : false,
              "showHeader" : false,
              "show" : true,
              "customSize" : "auto",
              "position" : "right-top",
              "inside" : true
            },
            "axisMode" : "multi",
            "totalSumMode" : "none",
            "tooltip" : {
              "content" : {
                "legend" : {
                  "showBinLabel" : true,
                  "measures" : [ ],
                  "showNullValues" : true,
                  "customizeLegend" : false,
                  "showPercentage" : true,
                  "showDimensions" : true,
                  "showMeasures" : true,
                  "dimensions" : [ ]
                }
              }
            },
            "visualizationType" : "stackhbar",
            "title" : {
              "fontSize" : 14,
              "subtitleFontSize" : 11,
              "label" : "Top Physicians by Procedure / Diagnosis",
              "align" : "center",
              "subtitleLabel" : ""
            },
            "binValues" : false,
            "trellis" : {
              "flipLabels" : false,
              "showGridLines" : true,
              "size" : [
                100,
                100
              ],
              "enable" : false,
              "type" : "x",
              "chartsPerLine" : 4
            },
            "columnProperties" : {
              "Name" : {
                "type" : "text",
                "parameters" : {
                  "styles" : {
                    "linkColor" : "#006dcc"
                  },
                  "alignment" : "left"
                }
              }
            },
            "columnMap" : {
              "split" : [
                "Procedure"
              ],
              "trellis" : [ ],
              "dimensionAxis" : [
                "Name",
                "Practitioner_NPI"
              ],
              "plots" : [
                "sum_Procedures"
              ]
            },
            "showActionMenu" : true,
            "measureAxis2" : {
              "sqrtScale" : false,
              "showTitle" : true,
              "showAxis" : true,
              "title" : "",
              "customDomain" : {
                "showDomain" : false
              }
            },
            "measureAxis1" : {
              "sqrtScale" : false,
              "showTitle" : true,
              "showAxis" : true,
              "title" : "",
              "customDomain" : {
                "showDomain" : false
              }
            },
            "normalize" : false,
            "theme" : "wave",
            "dimensionAxis" : {
              "showTitle" : true,
              "customSize" : "auto",
              "showAxis" : true,
              "title" : "",
              "icons" : {
                "useIcons" : false,
                "iconProps" : {
                  "fit" : "cover",
                  "column" : "",
                  "type" : "round"
                }
              }
            },
            "applyConditionalFormatting" : true
          },
          "type" : "chart"
        }
      },
      "Last_Name_2_1" : {
        "broadcastFacet" : true,
        "datasets" : [
          {
            "name" : "${App.Datasets.ITT_Target_Transformed_tp.Name}"
          }
        ],
        "isGlobal" : false,
        "label" : "Last_Name_2",
        "query" : {
          "query" : {
            "measures" : [
              [
                "sum",
                "Procedures"
              ]
            ],
            "limit" : 40,
            "groups" : [
              "Facility_Name"
            ],
            "order" : [
              [
                "sum_Procedures",
                {
                  "ascending" : false
                }
              ]
            ]
          },
          "version" : -1.0
        },
        "receiveFacetSource" : {
          "mode" : "all",
          "steps" : [ ]
        },
        "selectMode" : "single",
        "type" : "aggregateflex",
        "useGlobal" : true,
        "visualizationParameters" : {
          "parameters" : {
            "autoFitMode" : "keepLabels",
            "bins" : {
              "breakpoints" : {
                "high" : 100,
                "low" : 0
              },
              "bands" : {
                "high" : {
                  "color" : "#008000",
                  "label" : ""
                },
                "low" : {
                  "color" : "#B22222",
                  "label" : ""
                },
                "medium" : {
                  "color" : "#ffa500",
                  "label" : ""
                }
              }
            },
            "showValues" : true,
            "legend" : {
              "descOrder" : false,
              "showHeader" : false,
              "show" : false,
              "customSize" : "auto",
              "position" : "right-top",
              "inside" : false
            },
            "axisMode" : "multi",
            "tooltip" : {
              "content" : {
                "legend" : {
                  "showBinLabel" : true,
                  "measures" : [ ],
                  "showNullValues" : true,
                  "customizeLegend" : false,
                  "showPercentage" : true,
                  "showDimensions" : true,
                  "showMeasures" : true,
                  "dimensions" : [ ]
                }
              }
            },
            "visualizationType" : "hbar",
            "title" : {
              "fontSize" : 14,
              "subtitleFontSize" : 11,
              "label" : "Top Facility Volume",
              "align" : "center",
              "subtitleLabel" : ""
            },
            "binValues" : false,
            "trellis" : {
              "flipLabels" : false,
              "showGridLines" : true,
              "size" : [
                100,
                100
              ],
              "enable" : false,
              "type" : "x",
              "chartsPerLine" : 4
            },
            "columnMap" : {
              "trellis" : [ ],
              "dimensionAxis" : [
                "Facility_Name"
              ],
              "plots" : [
                "sum_Procedures"
              ]
            },
            "showActionMenu" : true,
            "measureAxis2" : {
              "sqrtScale" : false,
              "showTitle" : true,
              "showAxis" : true,
              "title" : "",
              "customDomain" : {
                "showDomain" : false
              }
            },
            "measureAxis1" : {
              "sqrtScale" : false,
              "showTitle" : false,
              "showAxis" : false,
              "title" : "",
              "customDomain" : {
                "showDomain" : false
              }
            },
            "theme" : "wave",
            "dimensionAxis" : {
              "showTitle" : false,
              "customSize" : "auto",
              "showAxis" : true,
              "title" : "",
              "icons" : {
                "useIcons" : false,
                "iconProps" : {
                  "fit" : "cover",
                  "column" : "",
                  "type" : "round"
                }
              }
            },
            "applyConditionalFormatting" : true
          },
          "type" : "chart"
        }
      },
      "Practitioner_Special_1" : {
        "broadcastFacet" : true,
        "datasets" : [
          {
            "name" : "${App.Datasets.ITT_Target_Transformed_tp.Name}"
          }
        ],
        "isGlobal" : false,
        "label" : "Practitioner_Special_2",
        "query" : {
          "query" : {
            "measures" : [
              [
                "count",
                "*"
              ]
            ],
            "groups" : [
              "Practitioner_Specialty"
            ],
            "order" : [
              [
                "count",
                {
                  "ascending" : false
                }
              ]
            ]
          },
          "version" : -1.0
        },
        "receiveFacetSource" : {
          "mode" : "all",
          "steps" : [ ]
        },
        "selectMode" : "single",
        "type" : "aggregateflex",
        "useGlobal" : true,
        "visualizationParameters" : {
          "parameters" : {
            "autoFitMode" : "keepLabels",
            "bins" : {
              "breakpoints" : {
                "high" : 100,
                "low" : 0
              },
              "bands" : {
                "high" : {
                  "color" : "#008000",
                  "label" : ""
                },
                "low" : {
                  "color" : "#B22222",
                  "label" : ""
                },
                "medium" : {
                  "color" : "#ffa500",
                  "label" : ""
                }
              }
            },
            "showValues" : true,
            "legend" : {
              "descOrder" : false,
              "showHeader" : false,
              "show" : true,
              "customSize" : "auto",
              "position" : "right-top",
              "inside" : false
            },
            "axisMode" : "multi",
            "tooltip" : {
              "content" : {
                "legend" : {
                  "showBinLabel" : true,
                  "measures" : [ ],
                  "showNullValues" : true,
                  "customizeLegend" : false,
                  "showPercentage" : true,
                  "showDimensions" : true,
                  "showMeasures" : true,
                  "dimensions" : [ ]
                }
              }
            },
            "visualizationType" : "hbar",
            "title" : {
              "fontSize" : 14,
              "subtitleFontSize" : 11,
              "label" : "Specialty Breakdown",
              "align" : "center",
              "subtitleLabel" : ""
            },
            "binValues" : false,
            "trellis" : {
              "flipLabels" : false,
              "showGridLines" : true,
              "size" : [
                100,
                100
              ],
              "enable" : false,
              "type" : "x",
              "chartsPerLine" : 4
            },
            "columnMap" : {
              "trellis" : [ ],
              "dimensionAxis" : [
                "Practitioner_Specialty"
              ],
              "plots" : [
                "count"
              ]
            },
            "showActionMenu" : true,
            "measureAxis2" : {
              "sqrtScale" : false,
              "showTitle" : true,
              "showAxis" : true,
              "title" : "",
              "customDomain" : {
                "showDomain" : false
              }
            },
            "measureAxis1" : {
              "sqrtScale" : false,
              "showTitle" : true,
              "showAxis" : true,
              "title" : "",
              "customDomain" : {
                "showDomain" : false
              }
            },
            "theme" : "wave",
            "dimensionAxis" : {
              "showTitle" : true,
              "customSize" : "auto",
              "showAxis" : true,
              "title" : "",
              "icons" : {
                "useIcons" : false,
                "iconProps" : {
                  "fit" : "cover",
                  "column" : "",
                  "type" : "round"
                }
              }
            },
            "applyConditionalFormatting" : true
          },
          "type" : "chart"
        }
      },
      "all_1" : {
        "broadcastFacet" : true,
        "datasets" : [
          {
            "name" : "${App.Datasets.ITT_Target_Transformed_tp.Name}"
          }
        ],
        "isGlobal" : false,
        "query" : {
          "query" : {
            "measures" : [
              [
                "count",
                "*"
              ]
            ]
          },
          "version" : -1.0
        },
        "receiveFacetSource" : {
          "mode" : "all",
          "steps" : [ ]
        },
        "selectMode" : "single",
        "type" : "aggregateflex",
        "useGlobal" : true,
        "visualizationParameters" : {
          "parameters" : {
            "autoFitMode" : "keepLabels",
            "bins" : {
              "breakpoints" : {
                "high" : 100,
                "low" : 0
              },
              "bands" : {
                "high" : {
                  "color" : "#008000",
                  "label" : ""
                },
                "low" : {
                  "color" : "#B22222",
                  "label" : ""
                },
                "medium" : {
                  "color" : "#ffa500",
                  "label" : ""
                }
              }
            },
            "showValues" : true,
            "legend" : {
              "descOrder" : false,
              "showHeader" : true,
              "show" : true,
              "customSize" : "auto",
              "position" : "right-top",
              "inside" : false
            },
            "axisMode" : "multi",
            "tooltip" : {
              "content" : {
                "legend" : {
                  "showBinLabel" : true,
                  "measures" : [ ],
                  "showNullValues" : true,
                  "customizeLegend" : false,
                  "showPercentage" : true,
                  "showDimensions" : true,
                  "showMeasures" : true,
                  "dimensions" : [ ]
                }
              }
            },
            "visualizationType" : "hbar",
            "title" : {
              "fontSize" : 14,
              "subtitleFontSize" : 11,
              "label" : "",
              "align" : "center",
              "subtitleLabel" : ""
            },
            "binValues" : false,
            "trellis" : {
              "flipLabels" : false,
              "showGridLines" : true,
              "size" : [
                100,
                100
              ],
              "enable" : false,
              "type" : "x",
              "chartsPerLine" : 4
            },
            "columnMap" : {
              "trellis" : [ ],
              "dimensionAxis" : [ ],
              "plots" : [
                "count"
              ]
            },
            "showActionMenu" : true,
            "measureAxis2" : {
              "sqrtScale" : false,
              "showTitle" : true,
              "showAxis" : true,
              "title" : "",
              "customDomain" : {
                "showDomain" : false
              }
            },
            "measureAxis1" : {
              "sqrtScale" : false,
              "showTitle" : true,
              "showAxis" : true,
              "title" : "",
              "customDomain" : {
                "showDomain" : false
              }
            },
            "theme" : "wave",
            "dimensionAxis" : {
              "showTitle" : true,
              "customSize" : "auto",
              "showAxis" : true,
              "title" : "",
              "icons" : {
                "useIcons" : false,
                "iconProps" : {
                  "fit" : "cover",
                  "column" : "",
                  "type" : "round"
                }
              }
            },
            "applyConditionalFormatting" : true
          },
          "type" : "chart"
        }
      },
      "lens_1_1" : {
        "broadcastFacet" : true,
        "datasets" : [
          {
            "name" : "${App.Datasets.ITT_Target_Transformed_tp.Name}"
          }
        ],
        "isGlobal" : false,
        "label" : "lens_1",
        "query" : {
          "query" : {
            "values" : [
              "Name",
              "Facility_Name",
              "Practitioner_Rank",
              "Facility_Rank",
              "Procedure",
              "Procedures",
              "City",
              "State",
              "Zip",
              "AccountId"
            ]
          },
          "version" : -1.0
        },
        "receiveFacetSource" : {
          "mode" : "all",
          "steps" : [ ]
        },
        "selectMode" : "single",
        "type" : "aggregateflex",
        "useGlobal" : true,
        "visualizationParameters" : {
          "options" : { },
          "parameters" : {
            "borderColor" : "#a8b7c7",
            "borderWidth" : 1,
            "cell" : {
              "backgroundColor" : "#ffffff",
              "fontColor" : "#16325c",
              "fontSize" : 12
            },
            "columnProperties" : { },
            "columns" : [ ],
            "customBulkActions" : [
              {
                "label" : "Send to Maps",
                "visualforce" : {
                  "name" : "VFMaps",
                  "namespace" : ""
                }
              }
            ],
            "header" : {
              "backgroundColor" : "#16325c",
              "fontColor" : "#ffffff",
              "fontSize" : 12
            },
            "innerMajorBorderColor" : "#54698d",
            "innerMinorBorderColor" : "#a8b7c7",
            "mode" : "fittocontainer",
            "numberOfLines" : 1,
            "showActionMenu" : true,
            "showRowIndexColumn" : true,
            "totals" : true,
            "verticalPadding" : 8
          },
          "type" : "table"
        }
      },
      "State_5_1" : {
        "broadcastFacet" : true,
        "datasets" : [
          {
            "name" : "${App.Datasets.ITT_Target_Transformed_tp.Name}"
          }
        ],
        "isGlobal" : false,
        "label" : "State_5",
        "query" : {
          "query" : {
            "measures" : [
              [
                "sum",
                "Procedures"
              ],
              [
                "unique",
                "Zip"
              ]
            ],
            "groups" : [
              "State"
            ]
          },
          "version" : -1.0
        },
        "receiveFacetSource" : {
          "mode" : "all",
          "steps" : [ ]
        },
        "selectMode" : "single",
        "type" : "aggregateflex",
        "useGlobal" : true,
        "visualizationParameters" : {
          "parameters" : {
            "autoFitMode" : "keepLabels",
            "legend" : {
              "descOrder" : false,
              "showHeader" : true,
              "show" : true,
              "customSize" : "auto",
              "position" : "right-top",
              "inside" : false
            },
            "autoZoom" : false,
            "axisMode" : "multi",
            "highColor" : "#1674D9",
            "tooltip" : {
              "content" : {
                "legend" : {
                  "showBinLabel" : true,
                  "measures" : [ ],
                  "showNullValues" : true,
                  "customizeLegend" : false,
                  "showPercentage" : true,
                  "showDimensions" : true,
                  "showMeasures" : true,
                  "dimensions" : [ ]
                }
              }
            },
            "projectionType" : "AlbersUSA",
            "lowColor" : "#C5DBF7",
            "visualizationType" : "bubblemap",
            "title" : {
              "fontSize" : 14,
              "subtitleFontSize" : 11,
              "label" : "Procedure Volume by State",
              "align" : "center",
              "subtitleLabel" : ""
            },
            "trellis" : {
              "flipLabels" : false,
              "showGridLines" : true,
              "size" : [
                100,
                100
              ],
              "enable" : false,
              "type" : "x",
              "chartsPerLine" : 4
            },
            "radiusRatio" : 5,
            "columnMap" : {
              "r" : [
                "sum_Procedures"
              ],
              "color" : [
                "unique_Zip"
              ],
              "trellis" : [ ],
              "plots" : [
                "State"
              ]
            },
            "showActionMenu" : true,
            "measureAxis2" : {
              "sqrtScale" : false,
              "showTitle" : true,
              "showAxis" : true,
              "title" : "",
              "customDomain" : {
                "showDomain" : false
              }
            },
            "measureAxis1" : {
              "sqrtScale" : false,
              "showTitle" : true,
              "showAxis" : true,
              "title" : "",
              "customDomain" : {
                "showDomain" : false
              }
            },
            "theme" : "wave",
            "map" : "US States",
            "dimensionAxis" : {
              "showTitle" : true,
              "customSize" : "auto",
              "showAxis" : true,
              "title" : "",
              "icons" : {
                "useIcons" : false,
                "iconProps" : {
                  "fit" : "cover",
                  "column" : "",
                  "type" : "round"
                }
              }
            },
            "applyConditionalFormatting" : true
          },
          "type" : "chart"
        }
      }
    },
    "widgetStyle" : {
      "backgroundColor" : "#091A3E",
      "borderColor" : "#98B1FF",
      "borderEdges" : [
        "all"
      ],
      "borderRadius" : 8,
      "borderWidth" : 2
    },
    "widgets" : {
      "link_3" : {
        "parameters" : {
          "destinationLink" : {
            "name" : "${App.Dashboards['ITT Network Dashboard'].Name}",
            "namespace" : "${Org.Namespace}"
          },
          "destinationType" : "dashboard",
          "fontSize" : 18,
          "includeState" : false,
          "text" : "NETWORK",
          "textAlignment" : "center",
          "textColor" : "#FFFFFF"
        },
        "type" : "link"
      },
      "filterpanel_1" : {
        "parameters" : {
          "filterItemOptions" : {
            "backgroundColor" : "#091A3E",
            "borderColor" : "#E6ECF2",
            "borderRadius" : 4,
            "borderWidth" : 1,
            "propertyColor" : "#FFFFFF",
            "valueColor" : "#FFFFFF"
          },
          "filters" : [ ],
          "itemsPerRow" : 7,
          "showAllFilters" : true,
          "title" : {
            "separatorColor" : "#E6ECF2",
            "text" : {
              "align" : "left",
              "color" : "#091A3E",
              "fontSize" : 16,
              "label" : "Filters"
            },
            "visible" : false
          }
        },
        "type" : "filterpanel"
      },
      "link_4" : {
        "parameters" : {
          "destinationLink" : {
            "name" : "${App.Dashboards['ITT Payermix Dashboard'].Name}",
            "namespace" : "${Org.Namespace}"
          },
          "destinationType" : "dashboard",
          "fontSize" : 18,
          "includeState" : false,
          "text" : "PAYER MIX",
          "textAlignment" : "center",
          "textColor" : "#FFFFFF"
        },
        "type" : "link"
      },
      "link_1" : {
        "parameters" : {
          "destinationLink" : {
            "name" : "${App.Dashboards['ITT Target Dashboard'].Name}",
            "namespace" : "${Org.Namespace}"
          },
          "destinationType" : "dashboard",
          "fontSize" : 18,
          "includeState" : false,
          "text" : "TARGET",
          "textAlignment" : "center",
          "textColor" : "#FFFFFF"
        },
        "type" : "link"
      },
      "link_2" : {
        "parameters" : {
          "destinationLink" : {
            "name" : "${App.Dashboards['ITT Sunshine Payments Dashboard'].Name}",
            "namespace" : "${Org.Namespace}"
          },
          "destinationType" : "dashboard",
          "fontSize" : 18,
          "includeState" : false,
          "text" : "SUNSHINE",
          "textAlignment" : "center",
          "textColor" : "#FFFFFF"
        },
        "type" : "link"
      },
      "table_1" : {
        "parameters" : {
          "borderColor" : "#54698d",
          "borderWidth" : 1,
          "cell" : {
            "backgroundColor" : "#16325c",
            "fontColor" : "#ffffff",
            "fontSize" : 12,
            "textWrap" : false
          },
          "columnProperties" : { },
          "columns" : [ ],
          "customBulkActions" : [
            {
              "label" : "Send to Maps",
              "visualforce" : {
                "name" : "VFMaps",
                "namespace" : ""
              }
            }
          ],
          "exploreLink" : true,
          "header" : {
            "backgroundColor" : "#000000",
            "fontColor" : "#ffffff",
            "fontSize" : 12,
            "textWrap" : false
          },
          "innerMajorBorderColor" : "#54698d",
          "innerMinorBorderColor" : "#54698d",
          "mode" : "fittocontainer",
          "numberOfLines" : 1,
          "showActionMenu" : true,
          "showRowIndexColumn" : true,
          "step" : "lens_1_1",
          "totals" : true,
          "verticalPadding" : 8
        },
        "type" : "table"
      },
      "container_1" : {
        "parameters" : {
          "alignmentX" : "left",
          "alignmentY" : "top",
          "fit" : "original"
        },
        "type" : "container"
      },
      "number_1" : {
        "parameters" : {
          "compact" : true,
          "exploreLink" : true,
          "measureField" : "count",
          "numberColor" : "#FFFFFF",
          "numberSize" : 24,
          "showActionMenu" : true,
          "step" : "all_1",
          "textAlignment" : "left",
          "title" : "Records",
          "titleColor" : "#FFFFFF",
          "titleSize" : 18,
          "tooltip" : {
            "customizeTooltip" : false
          }
        },
        "type" : "number"
      },
      "text_3" : {
        "parameters" : {
          "content" : {
            "richTextContent" : [
              {
                "attributes" : {
                  "color" : "#091a3e",
                  "size" : "16px"
                },
                "insert" : "Add text..."
              },
              {
                "attributes" : {
                  "align" : "left"
                },
                "insert" : "\n"
              }
            ]
          },
          "showActionMenu" : true
        },
        "type" : "text"
      },
      "text_2" : {
        "parameters" : {
          "content" : {
            "richTextContent" : [
              {
                "attributes" : {
                  "color" : "#ffffff",
                  "size" : "24px"
                },
                "insert" : "INTELLIGENT TARGETING TOOL"
              },
              {
                "attributes" : {
                  "align" : "center"
                },
                "insert" : "\n"
              }
            ]
          },
          "showActionMenu" : true
        },
        "type" : "text"
      },
      "chart_2" : {
        "parameters" : {
          "autoFitMode" : "keepLabels",
          "showValues" : true,
          "legend" : {
            "descOrder" : false,
            "showHeader" : true,
            "show" : false,
            "customSize" : "auto",
            "position" : "right-top",
            "inside" : false
          },
          "autoZoom" : true,
          "axisMode" : "multi",
          "highColor" : "#1674D9",
          "tooltip" : {
            "content" : {
              "legend" : {
                "showBinLabel" : true,
                "measures" : [ ],
                "showNullValues" : true,
                "customizeLegend" : false,
                "showPercentage" : true,
                "showDimensions" : true,
                "showMeasures" : true,
                "dimensions" : [ ]
              }
            }
          },
          "projectionType" : "AlbersUSA",
          "lowColor" : "#C5DBF7",
          "visualizationType" : "bubblemap",
          "exploreLink" : true,
          "title" : {
            "fontSize" : 14,
            "subtitleFontSize" : 11,
            "label" : "Procedure / Diagnosis Volume by State",
            "align" : "center",
            "subtitleLabel" : ""
          },
          "trellis" : {
            "flipLabels" : false,
            "showGridLines" : true,
            "size" : [
              100,
              100
            ],
            "enable" : false,
            "type" : "x",
            "chartsPerLine" : 4
          },
          "radiusRatio" : 5,
          "columnMap" : {
            "r" : [
              "sum_Procedures"
            ],
            "color" : [
              "unique_Zip"
            ],
            "trellis" : [ ],
            "plots" : [
              "State"
            ]
          },
          "showActionMenu" : false,
          "measureAxis2" : {
            "sqrtScale" : false,
            "showTitle" : true,
            "showAxis" : true,
            "title" : "",
            "customDomain" : {
              "showDomain" : false
            }
          },
          "measureAxis1" : {
            "sqrtScale" : false,
            "showTitle" : true,
            "showAxis" : true,
            "title" : "",
            "customDomain" : {
              "showDomain" : false
            }
          },
          "theme" : "dark",
          "step" : "State_5_1",
          "map" : "US States",
          "dimensionAxis" : {
            "showTitle" : true,
            "customSize" : "auto",
            "showAxis" : true,
            "title" : "",
            "icons" : {
              "useIcons" : false,
              "iconProps" : {
                "fit" : "cover",
                "column" : "",
                "type" : "round"
              }
            }
          },
          "applyConditionalFormatting" : true
        },
        "type" : "chart"
      },
      "chart_1" : {
        "parameters" : {
          "autoFitMode" : "keepLabels",
          "bins" : {
            "breakpoints" : {
              "high" : 100,
              "low" : 0
            },
            "bands" : {
              "high" : {
                "color" : "#008000",
                "label" : ""
              },
              "low" : {
                "color" : "#B22222",
                "label" : ""
              },
              "medium" : {
                "color" : "#ffa500",
                "label" : ""
              }
            }
          },
          "showValues" : true,
          "legend" : {
            "descOrder" : false,
            "showHeader" : false,
            "show" : false,
            "customSize" : "auto",
            "position" : "right-top",
            "inside" : false
          },
          "axisMode" : "multi",
          "tooltip" : {
            "content" : {
              "legend" : {
                "showBinLabel" : true,
                "measures" : [ ],
                "showNullValues" : true,
                "customizeLegend" : false,
                "showPercentage" : true,
                "showDimensions" : true,
                "showMeasures" : true,
                "dimensions" : [ ]
              }
            }
          },
          "visualizationType" : "hbar",
          "exploreLink" : true,
          "title" : {
            "fontSize" : 14,
            "subtitleFontSize" : 11,
            "label" : "Top Facility Volume",
            "align" : "center",
            "subtitleLabel" : ""
          },
          "binValues" : false,
          "trellis" : {
            "flipLabels" : false,
            "showGridLines" : true,
            "size" : [
              100,
              100
            ],
            "enable" : false,
            "type" : "x",
            "chartsPerLine" : 4
          },
          "columnMap" : {
            "trellis" : [ ],
            "dimensionAxis" : [
              "Facility_Name"
            ],
            "plots" : [
              "sum_Procedures"
            ]
          },
          "showActionMenu" : true,
          "measureAxis2" : {
            "sqrtScale" : false,
            "showTitle" : true,
            "showAxis" : true,
            "title" : "",
            "customDomain" : {
              "showDomain" : false
            }
          },
          "measureAxis1" : {
            "sqrtScale" : false,
            "showTitle" : false,
            "showAxis" : false,
            "title" : "",
            "customDomain" : {
              "showDomain" : false
            }
          },
          "theme" : "dark",
          "step" : "Last_Name_2_1",
          "dimensionAxis" : {
            "showTitle" : false,
            "customSize" : "auto",
            "showAxis" : true,
            "title" : "",
            "icons" : {
              "useIcons" : false,
              "iconProps" : {
                "fit" : "cover",
                "column" : "",
                "type" : "round"
              }
            }
          },
          "applyConditionalFormatting" : true
        },
        "type" : "chart"
      },
      "chart_4" : {
        "parameters" : {
          "autoFitMode" : "keepLabels",
          "bins" : {
            "breakpoints" : {
              "high" : 100,
              "low" : 0
            },
            "bands" : {
              "high" : {
                "color" : "#008000",
                "label" : ""
              },
              "low" : {
                "color" : "#B22222",
                "label" : ""
              },
              "medium" : {
                "color" : "#ffa500",
                "label" : ""
              }
            }
          },
          "showValues" : true,
          "legend" : {
            "descOrder" : false,
            "showHeader" : false,
            "show" : true,
            "customSize" : "auto",
            "position" : "right-top",
            "inside" : true
          },
          "axisMode" : "multi",
          "totalSumMode" : "none",
          "tooltip" : {
            "content" : {
              "legend" : {
                "showBinLabel" : true,
                "measures" : [ ],
                "showNullValues" : true,
                "customizeLegend" : false,
                "showPercentage" : true,
                "showDimensions" : true,
                "showMeasures" : true,
                "dimensions" : [ ]
              }
            }
          },
          "visualizationType" : "stackhbar",
          "exploreLink" : true,
          "title" : {
            "fontSize" : 14,
            "subtitleFontSize" : 11,
            "label" : "Top Physicians by Procedure / Diagnosis",
            "align" : "center",
            "subtitleLabel" : ""
          },
          "binValues" : false,
          "trellis" : {
            "flipLabels" : false,
            "showGridLines" : true,
            "size" : [
              100,
              100
            ],
            "enable" : false,
            "type" : "x",
            "chartsPerLine" : 4
          },
          "columnProperties" : {
            "Name" : {
              "type" : "text",
              "parameters" : {
                "styles" : {
                  "linkColor" : "#006dcc"
                },
                "alignment" : "left"
              }
            }
          },
          "columnMap" : {
            "split" : [
              "Procedure"
            ],
            "trellis" : [ ],
            "dimensionAxis" : [
              "Name",
              "Practitioner_NPI"
            ],
            "plots" : [
              "sum_Procedures"
            ]
          },
          "showActionMenu" : true,
          "measureAxis2" : {
            "sqrtScale" : false,
            "showTitle" : true,
            "showAxis" : true,
            "title" : "",
            "customDomain" : {
              "showDomain" : false
            }
          },
          "measureAxis1" : {
            "sqrtScale" : false,
            "showTitle" : true,
            "showAxis" : true,
            "title" : "",
            "customDomain" : {
              "showDomain" : false
            }
          },
          "normalize" : false,
          "theme" : "dark",
          "step" : "Procedure_2_1",
          "dimensionAxis" : {
            "showTitle" : true,
            "customSize" : "auto",
            "showAxis" : true,
            "title" : "Practitioner",
            "icons" : {
              "useIcons" : false,
              "iconProps" : {
                "fit" : "cover",
                "column" : "",
                "type" : "round"
              }
            }
          },
          "applyConditionalFormatting" : true
        },
        "type" : "chart"
      },
      "chart_3" : {
        "parameters" : {
          "autoFitMode" : "keepLabels",
          "bins" : {
            "breakpoints" : {
              "high" : 100,
              "low" : 0
            },
            "bands" : {
              "high" : {
                "color" : "#008000",
                "label" : ""
              },
              "low" : {
                "color" : "#B22222",
                "label" : ""
              },
              "medium" : {
                "color" : "#ffa500",
                "label" : ""
              }
            }
          },
          "showValues" : true,
          "legend" : {
            "descOrder" : false,
            "showHeader" : false,
            "show" : false,
            "customSize" : "auto",
            "position" : "right-top",
            "inside" : false
          },
          "axisMode" : "multi",
          "tooltip" : {
            "content" : {
              "legend" : {
                "showBinLabel" : true,
                "measures" : [ ],
                "showNullValues" : true,
                "customizeLegend" : false,
                "showPercentage" : true,
                "showDimensions" : true,
                "showMeasures" : true,
                "dimensions" : [ ]
              }
            }
          },
          "visualizationType" : "hbar",
          "exploreLink" : true,
          "title" : {
            "fontSize" : 14,
            "subtitleFontSize" : 11,
            "label" : "Specialty Breakdown",
            "align" : "center",
            "subtitleLabel" : ""
          },
          "binValues" : false,
          "trellis" : {
            "flipLabels" : false,
            "showGridLines" : true,
            "size" : [
              100,
              100
            ],
            "enable" : false,
            "type" : "x",
            "chartsPerLine" : 4
          },
          "columnMap" : {
            "trellis" : [ ],
            "dimensionAxis" : [
              "Practitioner_Specialty"
            ],
            "plots" : [
              "count"
            ]
          },
          "showActionMenu" : true,
          "measureAxis2" : {
            "sqrtScale" : false,
            "showTitle" : true,
            "showAxis" : true,
            "title" : "",
            "customDomain" : {
              "showDomain" : false
            }
          },
          "measureAxis1" : {
            "sqrtScale" : true,
            "showTitle" : false,
            "showAxis" : false,
            "title" : "",
            "customDomain" : {
              "showDomain" : false
            }
          },
          "theme" : "dark",
          "step" : "Practitioner_Special_1",
          "dimensionAxis" : {
            "showTitle" : false,
            "customSize" : "auto",
            "showAxis" : true,
            "title" : "",
            "icons" : {
              "useIcons" : false,
              "iconProps" : {
                "fit" : "cover",
                "column" : "",
                "type" : "round"
              }
            }
          },
          "applyConditionalFormatting" : true
        },
        "type" : "chart"
      }
    }
  }
}